<?xml version="1.0" encoding="UTF-8"?>
<actions>
        <action>
            <actionName>run</actionName>
            <packagings>
                <packaging>jar</packaging>
            </packagings>
            <goals>
                <goal>process-classes</goal>
                <goal>org.codehaus.mojo:exec-maven-plugin:1.2.1:exec</goal>
            </goals>
            <properties>
                <exec.args>-classpath %classpath oeg.LawORDate.Main "Tal y como establece el artículo 3.e de la Ley 22/2011, de 28 de julio, de residuos y suelos contaminados, (BOE: 29/07/2011) es «Residuo peligroso»: residuo que presenta una o varias de las características peligrosas enumeradas en el anexo III, y aquél que pueda aprobar el Gobierno de conformidad con lo establecido en la normativa europea o en los convenios internacionales de los que España sea parte, así como los recipientes y envases que los hayan contenido."</exec.args>
                <exec.executable>java</exec.executable>
            </properties>
        </action>
        <action>
            <actionName>debug</actionName>
            <packagings>
                <packaging>jar</packaging>
            </packagings>
            <goals>
                <goal>process-classes</goal>
                <goal>org.codehaus.mojo:exec-maven-plugin:1.2.1:exec</goal>
            </goals>
            <properties>
                <exec.args>-Xdebug -Xrunjdwp:transport=dt_socket,server=n,address=${jpda.address} -classpath %classpath oeg.LawORDate.Main "Tal y como establece el artículo 3.e de la Ley 22/2011, de 28 de julio, de residuos y suelos contaminados, (BOE: 29/07/2011) es «Residuo peligroso»: residuo que presenta una o varias de las características peligrosas enumeradas en el anexo III, y aquél que pueda aprobar el Gobierno de conformidad con lo establecido en la normativa europea o en los convenios internacionales de los que España sea parte, así como los recipientes y envases que los hayan contenido."</exec.args>
                <exec.executable>java</exec.executable>
                <jpda.listen>true</jpda.listen>
            </properties>
        </action>
        <action>
            <actionName>profile</actionName>
            <packagings>
                <packaging>jar</packaging>
            </packagings>
            <goals>
                <goal>process-classes</goal>
                <goal>org.codehaus.mojo:exec-maven-plugin:1.2.1:exec</goal>
            </goals>
            <properties>
                <exec.args>-classpath %classpath oeg.LawORDate.Main "Tal y como establece el artículo 3.e de la Ley 22/2011, de 28 de julio, de residuos y suelos contaminados, (BOE: 29/07/2011) es «Residuo peligroso»: residuo que presenta una o varias de las características peligrosas enumeradas en el anexo III, y aquél que pueda aprobar el Gobierno de conformidad con lo establecido en la normativa europea o en los convenios internacionales de los que España sea parte, así como los recipientes y envases que los hayan contenido."</exec.args>
                <exec.executable>java</exec.executable>
            </properties>
        </action>
    </actions>
